lectures/l16-ROM/rom.v
`timescale 1ns / 1ps


//guardar -- 0 1 1 2 3 5 8 13 21 34  

module rom (
			input [3:0] add,
            output [5:0] out        
            );

  
  	reg[5:0] rom[9:0];

	initial
	begin 
		$readmemb("data.bin", rom, 0,9);
	end


	assign out = rom[add];


endmodule


module rom_tb ();

	reg [3:0] add;
	reg [5:0] out;
    
   rom rom0 (
   			.add(add),
   			.out(out)
            );   

   initial begin

      $dumpfile("dump.vcd");
      $dumpvars;
      

      add = 0;
      #1

      add = 1;
      #1
      add = 2;
      #1
      add = 3;
      #1
      add = 4;
      #1
      add = 5;
      #1
      add = 6;
      #1
      add = 7;
      #1
      add = 8;
      #1
      add = 9;
      #1


      $finish;

    end 
 
endmodule

lectures/l16-ROM/dump.vcd
$date
	Tue Nov  5 15:41:06 2019
$end
$version
	Icarus Verilog
$end
$timescale
	1ps
$end
$scope module rom_tb $end
$var wire 6 ! out [5:0] $end
$var reg 4 " add [3:0] $end
$scope module rom0 $end
$var wire 4 # add [3:0] $end
$var wire 6 $ out [5:0] $end
$upscope $end
$upscope $end
$enddefinitions $end
#0
$dumpvars
b0 $
b0 #
b0 "
b0 !
$end
#1000
b1 !
b1 $
b1 "
b1 #
#2000
b10 "
b10 #
#3000
b10 !
b10 $
b11 "
b11 #
#4000
b11 !
b11 $
b100 "
b100 #
#5000
b101 !
b101 $
b101 "
b101 #
#6000
b1000 !
b1000 $
b110 "
b110 #
#7000
b1101 !
b1101 $
b111 "
b111 #
#8000
b10101 !
b10101 $
b1000 "
b1000 #
#9000
b100010 !
b100010 $
b1001 "
b1001 #
