lectures/l12_booth/booth_mul.v
`timescale 1ns / 1ps

module booth_mul (
                    input         clk,
                    input         rst,
                     
                    input [31:0]   M, 
                    input [31:0]   m,
                    output[63:0]   p,
                    output reg	done

                    );

   reg [64:0]       pm;
   reg 				pc;
   reg [5:0]		counter;

   assign p = pm[64:1];

	always@(posedge clk)
    	if(rst) begin
       		pm <= 65'b0;
        	pc <= 0;
        	counter <=0;
        	done <= 0;
   		end
    	else begin
    		counter <= counter +1;
     		pc <= pc+1;
     		case(pc)
   				0: pm[32:1] <= m;
   				1: begin
   					case(pm[1:0]) 
   						2'b01 : begin 
							pm[64:32] <= (pm[64:33] + M);
							pm[31:0]  <= pm[32:1];
						end
						2'b10 : begin
							pm[64:32] <= pm[64:33] - M;
							pm[31:0] <= pm[32:1];
						end

						default: begin 
							pm[63:0] <= pm[64:1];
						end

					endcase // pm[1:0]


					if(counter != 32)
						pc <= pc;
					else if (counter == 32) begin
						pc<=pc;
						done <= 1;
						counter <= 32;
					end
   				end
   			endcase
   		end



  
endmodule


module booth_mul_tb ();

   reg clk, rst;
   reg [31:0] m, M;
   wire [63:0] p;
   wire        done;
   
   booth_mul mult0 (
                       .clk(clk),
                       .rst(rst),
                     
                       .M(M), 
                       .m(m),
                       .p(p),
                       .done(done)
                     );   

   initial begin

      $dumpfile("dump.vcd");
      $dumpvars;
      
      rst = 1;
      clk = 1;

      M=32'd6;
      m=32'd2;

      @(posedge clk) #1 rst=0;

      @(posedge done) $display("%d", p);
      
      @(posedge clk) $finish;
   end
   
   always #10 clk = ~clk;
 
endmodule

lectures/l12_booth/dump.vcd
$date
	Tue Oct 29 16:41:06 2019
$end
$version
	Icarus Verilog
$end
$timescale
	1ps
$end
$scope module booth_mul_tb $end
$var wire 64 ! p [63:0] $end
$var wire 1 " done $end
$var reg 32 # M [31:0] $end
$var reg 1 $ clk $end
$var reg 32 % m [31:0] $end
$var reg 1 & rst $end
$scope module mult0 $end
$var wire 32 ' M [31:0] $end
$var wire 1 $ clk $end
$var wire 32 ( m [31:0] $end
$var wire 1 & rst $end
$var wire 64 ) p [63:0] $end
$var reg 6 * counter [5:0] $end
$var reg 1 " done $end
$var reg 1 + pc $end
$var reg 65 , pm [64:0] $end
$upscope $end
$upscope $end
$enddefinitions $end
#0
$dumpvars
b0 ,
0+
b0 *
b0 )
b10 (
b110 '
1&
b10 %
1$
b110 #
0"
b0 !
$end
#10000
0$
#20000
1$
#21000
0&
#30000
0$
#40000
b10 !
b10 )
b100 ,
1+
b1 *
1$
#50000
0$
#60000
b1 !
b1 )
b10 ,
1+
b10 *
1$
#70000
0$
#80000
b1111111111111111111111111111110100000000000000000000000000000000 !
b1111111111111111111111111111110100000000000000000000000000000000 )
b11111111111111111111111111111101000000000000000000000000000000001 ,
1+
b11 *
1$
#90000
0$
#100000
b1000000000000000000000000000000110000000000000000000000000000000 !
b1000000000000000000000000000000110000000000000000000000000000000 )
b10000000000000000000000000000001100000000000000000000000000000000 ,
1+
b100 *
1$
#110000
0$
#120000
b1100000000000000000000000000000011000000000000000000000000000000 !
b1100000000000000000000000000000011000000000000000000000000000000 )
b11000000000000000000000000000000110000000000000000000000000000000 ,
1+
b101 *
1$
#130000
0$
#140000
b1110000000000000000000000000000001100000000000000000000000000000 !
b1110000000000000000000000000000001100000000000000000000000000000 )
b11100000000000000000000000000000011000000000000000000000000000000 ,
1+
b110 *
1$
#150000
0$
#160000
b1111000000000000000000000000000000110000000000000000000000000000 !
b1111000000000000000000000000000000110000000000000000000000000000 )
b11110000000000000000000000000000001100000000000000000000000000000 ,
1+
b111 *
1$
#170000
0$
#180000
b1111100000000000000000000000000000011000000000000000000000000000 !
b1111100000000000000000000000000000011000000000000000000000000000 )
b11111000000000000000000000000000000110000000000000000000000000000 ,
1+
b1000 *
1$
#190000
0$
#200000
b1111110000000000000000000000000000001100000000000000000000000000 !
b1111110000000000000000000000000000001100000000000000000000000000 )
b11111100000000000000000000000000000011000000000000000000000000000 ,
1+
b1001 *
1$
#210000
0$
#220000
b1111111000000000000000000000000000000110000000000000000000000000 !
b1111111000000000000000000000000000000110000000000000000000000000 )
b11111110000000000000000000000000000001100000000000000000000000000 ,
1+
b1010 *
1$
#230000
0$
#240000
b1111111100000000000000000000000000000011000000000000000000000000 !
b1111111100000000000000000000000000000011000000000000000000000000 )
b11111111000000000000000000000000000000110000000000000000000000000 ,
1+
b1011 *
1$
#250000
0$
#260000
b1111111110000000000000000000000000000001100000000000000000000000 !
b1111111110000000000000000000000000000001100000000000000000000000 )
b11111111100000000000000000000000000000011000000000000000000000000 ,
1+
b1100 *
1$
#270000
0$
#280000
b1111111111000000000000000000000000000000110000000000000000000000 !
b1111111111000000000000000000000000000000110000000000000000000000 )
b11111111110000000000000000000000000000001100000000000000000000000 ,
1+
b1101 *
1$
#290000
0$
#300000
b1111111111100000000000000000000000000000011000000000000000000000 !
b1111111111100000000000000000000000000000011000000000000000000000 )
b11111111111000000000000000000000000000000110000000000000000000000 ,
1+
b1110 *
1$
#310000
0$
#320000
b1111111111110000000000000000000000000000001100000000000000000000 !
b1111111111110000000000000000000000000000001100000000000000000000 )
b11111111111100000000000000000000000000000011000000000000000000000 ,
1+
b1111 *
1$
#330000
0$
#340000
b1111111111111000000000000000000000000000000110000000000000000000 !
b1111111111111000000000000000000000000000000110000000000000000000 )
b11111111111110000000000000000000000000000001100000000000000000000 ,
1+
b10000 *
1$
#350000
0$
#360000
b1111111111111100000000000000000000000000000011000000000000000000 !
b1111111111111100000000000000000000000000000011000000000000000000 )
b11111111111111000000000000000000000000000000110000000000000000000 ,
1+
b10001 *
1$
#370000
0$
#380000
b1111111111111110000000000000000000000000000001100000000000000000 !
b1111111111111110000000000000000000000000000001100000000000000000 )
b11111111111111100000000000000000000000000000011000000000000000000 ,
1+
b10010 *
1$
#390000
0$
#400000
b1111111111111111000000000000000000000000000000110000000000000000 !
b1111111111111111000000000000000000000000000000110000000000000000 )
b11111111111111110000000000000000000000000000001100000000000000000 ,
1+
b10011 *
1$
#410000
0$
#420000
b1111111111111111100000000000000000000000000000011000000000000000 !
b1111111111111111100000000000000000000000000000011000000000000000 )
b11111111111111111000000000000000000000000000000110000000000000000 ,
1+
b10100 *
1$
#430000
0$
#440000
b1111111111111111110000000000000000000000000000001100000000000000 !
b1111111111111111110000000000000000000000000000001100000000000000 )
b11111111111111111100000000000000000000000000000011000000000000000 ,
1+
b10101 *
1$
#450000
0$
#460000
b1111111111111111111000000000000000000000000000000110000000000000 !
b1111111111111111111000000000000000000000000000000110000000000000 )
b11111111111111111110000000000000000000000000000001100000000000000 ,
1+
b10110 *
1$
#470000
0$
#480000
b1111111111111111111100000000000000000000000000000011000000000000 !
b1111111111111111111100000000000000000000000000000011000000000000 )
b11111111111111111111000000000000000000000000000000110000000000000 ,
1+
b10111 *
1$
#490000
0$
#500000
b1111111111111111111110000000000000000000000000000001100000000000 !
b1111111111111111111110000000000000000000000000000001100000000000 )
b11111111111111111111100000000000000000000000000000011000000000000 ,
1+
b11000 *
1$
#510000
0$
#520000
b1111111111111111111111000000000000000000000000000000110000000000 !
b1111111111111111111111000000000000000000000000000000110000000000 )
b11111111111111111111110000000000000000000000000000001100000000000 ,
1+
b11001 *
1$
#530000
0$
#540000
b1111111111111111111111100000000000000000000000000000011000000000 !
b1111111111111111111111100000000000000000000000000000011000000000 )
b11111111111111111111111000000000000000000000000000000110000000000 ,
1+
b11010 *
1$
#550000
0$
#560000
b1111111111111111111111110000000000000000000000000000001100000000 !
b1111111111111111111111110000000000000000000000000000001100000000 )
b11111111111111111111111100000000000000000000000000000011000000000 ,
1+
b11011 *
1$
#570000
0$
#580000
b1111111111111111111111111000000000000000000000000000000110000000 !
b1111111111111111111111111000000000000000000000000000000110000000 )
b11111111111111111111111110000000000000000000000000000001100000000 ,
1+
b11100 *
1$
#590000
0$
#600000
b1111111111111111111111111100000000000000000000000000000011000000 !
b1111111111111111111111111100000000000000000000000000000011000000 )
b11111111111111111111111111000000000000000000000000000000110000000 ,
1+
b11101 *
1$
#610000
0$
#620000
b1111111111111111111111111110000000000000000000000000000001100000 !
b1111111111111111111111111110000000000000000000000000000001100000 )
b11111111111111111111111111100000000000000000000000000000011000000 ,
1+
b11110 *
1$
#630000
0$
#640000
b1111111111111111111111111111000000000000000000000000000000110000 !
b1111111111111111111111111111000000000000000000000000000000110000 )
b11111111111111111111111111110000000000000000000000000000001100000 ,
1+
b11111 *
1$
#650000
0$
#660000
b1111111111111111111111111111100000000000000000000000000000011000 !
b1111111111111111111111111111100000000000000000000000000000011000 )
b11111111111111111111111111111000000000000000000000000000000110000 ,
1+
b100000 *
1$
#670000
0$
#680000
b1111111111111111111111111111110000000000000000000000000000001100 !
b1111111111111111111111111111110000000000000000000000000000001100 )
1"
b11111111111111111111111111111100000000000000000000000000000011000 ,
1+
b100000 *
1$
#690000
0$
#700000
b1111111111111111111111111111111000000000000000000000000000000110 !
b1111111111111111111111111111111000000000000000000000000000000110 )
b11111111111111111111111111111110000000000000000000000000000001100 ,
1+
b100000 *
1$
