lectures/l9/Verilog/full_adder.v
module full_adder
	(  
		input  	a,
		input  	b,
	 	input   c_in,
	 	output  c_out,
	    output  res
   );


   assign res = a ^ b ^c_in;

   assign c_out = (a ^ b) & c_in | (a & b);

endmodule

lectures/l9/Verilog/multi.v
module multi
	(
		input  [1:0] 	a,
		input  [1:0] 	b,
	    output [3:0]  	s
   );


   wire pp0[1:0] , pp1 [1:0];
   wire carry;

   assign pp0[0]  = a[0] & b[0];
   assign pp0[1]  = a[1] & b[0];

   assign s[0] = pp0[0];

   assign pp1[0] = a[0] & b[1];
   assign pp1[1] = a[1] & b[1];


   full_adder adder1(

   			.a(pp0[1]),
   			.b(pp1[0]),
   			.c_in(1'b0),
   			.c_out(carry),
   			.res(s[1])
   );


  full_adder adder2(

			.a(carry),
			.b(pp1[1]),
			.c_in(1'b0),
			.c_out(s[3]),
			.res(s[2])
   );


endmodule

lectures/l9/Verilog/multi_tb.v
module multi_tb;

  parameter T = 10;

   reg [1:0]  a;
   reg [1:0]  b;
   wire[3:0]  s;

   
   // Instantiate the Unit Under Test (UUT)
   multi uut (
      .a(a),
      .b(b),
      .s(s)
		);
 
  
      always #T    a[0] = ! a[0];

      always #(2*T) a[1] = !a[1];

      always #(4*T) b[0] = !b[0];
      
      always #(6*T) b[1] = !b[1];

    initial begin
      $dumpfile("multi.vcd");
      $dumpvars(0, multi_tb);

      a = 0;
      b = 0;


      #(17*T)
      $finish;


      end 

endmodule

lectures/l9/Verilog/multi.vcd
$date
	Thu Oct 17 17:03:49 2019
$end
$version
	Icarus Verilog
$end
$timescale
	1s
$end
$scope module multi_tb $end
$var wire 4 ! s [3:0] $end
$var reg 2 " a [1:0] $end
$var reg 2 # b [1:0] $end
$scope module uut $end
$var wire 2 $ a [1:0] $end
$var wire 2 % b [1:0] $end
$var wire 4 & s [3:0] $end
$var wire 1 ' carry $end
$scope module adder1 $end
$var wire 1 ( a $end
$var wire 1 ) b $end
$var wire 1 * c_in $end
$var wire 1 ' c_out $end
$var wire 1 + res $end
$upscope $end
$scope module adder2 $end
$var wire 1 ' a $end
$var wire 1 , b $end
$var wire 1 - c_in $end
$var wire 1 . c_out $end
$var wire 1 / res $end
$upscope $end
$upscope $end
$upscope $end
$enddefinitions $end
#0
$dumpvars
0/
0.
0-
0,
0+
0*
0)
0(
0'
b0 &
b0 %
b0 $
b0 #
b0 "
b0 !
$end
#10
b1 "
b1 $
#20
b10 "
b10 $
#30
b11 "
b11 $
#40
b0 "
b0 $
b1 #
b1 %
#50
b1 !
b1 &
b1 "
b1 $
#60
1+
1/
b110 !
b110 &
1(
1,
b10 "
b10 $
b11 #
b11 %
#70
0/
1.
0+
1'
b1001 !
b1001 &
1)
b11 "
b11 $
#80
0/
0.
0'
0)
0,
b0 !
b0 &
0(
b0 "
b0 $
b10 #
b10 %
#90
b10 !
b10 &
1+
1)
b1 "
b1 $
#100
0+
b100 !
b100 &
1/
0)
1,
b10 "
b10 $
