lectures/l13/div.v
`timescale 1ns / 1ps

module div (
                     input         clk,
                     input         rst,
                     input         start,
                     input 	[7:0]   D, 
                     input  [7:0]   d,
                     output reg [7:0] q,
                     output reg [7:0] r,
                     output reg     done
                     );

   reg [3:0]                    counter;
   reg [7:0] 					d_reg;
   reg [15:0]					D_reg;
   reg 							q_in;
   reg [7:0]					sub;



   	always@(posedge clk)
    	if(rst) begin
    		counter <= 4'd0;
    		done = 0;
    	end
    	else if (start)
    		counter <= 4'd0;

    	else if (counter == 4'd8) begin
    		done <= 1;
     		q <= D_reg[7:0];
     		r <= D_reg[15:8];
     	end
    	else if (counter != 4'd8)begin
    		counter <= counter + 1'b1;
        end

   

    always@(posedge clk)
    	if(rst)begin
    		d_reg <= 8'd0;
        	
        end
    	else if (start) begin
        	d_reg <= d;
        end



    always@*   
    	if(D_reg[14:7] >= d_reg)begin
    		q_in = 1;
    		sub = D_reg[14:7] - d_reg;
    	end
    	else begin
    		q_in = 0;
    		sub = D_reg[14:7];
    	end

   
     always@(posedge clk)
     	if(rst)
     		D_reg <= 16'd0;
     	else if(start)
     		D_reg <= {8'd0, D};  
     	else if(counter != 4'd8) begin  
        	D_reg <= {sub, D_reg[6:0], q_in}; 
     	end

endmodule


module div_tb ();

   reg clk, rst;
   reg [7:0] d, D;
   wire [7:0] r, q;
   reg         start;
   wire        done;
   
   div mult0 (
                       .clk(clk),
                       .rst(rst),
                     
                       .D(D), 
                       .d(d),
                       .r(r),
                       .q(q),	
                       .start(start),
                       .done(done)
                     );   

   initial begin

      $dumpfile("dump.vcd");
      $dumpvars;
      
      rst = 1;
      clk = 1;
      start = 0;

      D=8'd5;
      d=8'd2;

      @(posedge clk) #1 rst=0;

      #5 @(posedge clk) #1 start=1;
      @(posedge clk) #1 start=0;

      @(posedge done) $display("%d\n%d", q, r);
      
      @(posedge clk) $finish;
   end
   
   always #10 clk = ~clk;
 
endmodule

lectures/l13/dump.vcd
$date
	Thu Oct 24 17:43:39 2019
$end
$version
	Icarus Verilog
$end
$timescale
	1ps
$end
$scope module div_tb $end
$var wire 8 ! r [7:0] $end
$var wire 8 " q [7:0] $end
$var wire 1 # done $end
$var reg 8 $ D [7:0] $end
$var reg 1 % clk $end
$var reg 8 & d [7:0] $end
$var reg 1 ' rst $end
$var reg 1 ( start $end
$scope module mult0 $end
$var wire 8 ) D [7:0] $end
$var wire 1 % clk $end
$var wire 8 * d [7:0] $end
$var wire 1 ' rst $end
$var wire 1 ( start $end
$var reg 16 + D_reg [15:0] $end
$var reg 4 , counter [3:0] $end
$var reg 8 - d_reg [7:0] $end
$var reg 1 # done $end
$var reg 8 . q [7:0] $end
$var reg 1 / q_in $end
$var reg 8 0 r [7:0] $end
$var reg 8 1 sub [7:0] $end
$upscope $end
$upscope $end
$enddefinitions $end
#0
$dumpvars
b0 1
bx 0
1/
bx .
b0 -
b0 ,
b0 +
b10 *
b101 )
0(
1'
b10 &
1%
b101 $
0#
bx "
bx !
$end
#10000
0%
#20000
1%
#21000
0'
#30000
0%
#40000
b1 ,
b1 +
1%
#41000
1(
#50000
0%
#60000
0/
b101 +
b10 -
b0 ,
1%
#61000
0(
#70000
0%
#80000
b1 ,
b1010 +
1%
#90000
0%
#100000
b10100 +
b10 ,
1%
#110000
0%
#120000
b11 ,
b101000 +
1%
#130000
0%
#140000
b1010000 +
b100 ,
1%
#150000
0%
#160000
b1 1
b101 ,
b10100000 +
1%
#170000
0%
#180000
b0 1
1/
b101000000 +
b110 ,
1%
#190000
0%
#200000
b1 1
0/
b111 ,
b10000001 +
1%
#210000
0%
#220000
b0 1
1/
b100000010 +
b1000 ,
1%
#230000
0%
#240000
b1 !
b1 0
b10 "
b10 .
1#
1%
